{
  "namespaces": [
    "public"
  ],
  "name": "public",
  "tables": [
    {
      "columns": {
        "id": {
          "name": "id",
          "type": "serial",
          "unsigned": false,
          "autoincrement": true,
          "primary": true,
          "nullable": false,
          "mappedType": "integer"
        },
        "name": {
          "name": "name",
          "type": "varchar(255)",
          "unsigned": false,
          "autoincrement": false,
          "primary": false,
          "nullable": false,
          "length": 255,
          "mappedType": "string"
        }
      },
      "name": "pokemon",
      "schema": "public",
      "indexes": [
        {
          "columnNames": [
            "name"
          ],
          "composite": false,
          "keyName": "pokemon_name_unique",
          "constraint": true,
          "primary": false,
          "unique": true
        },
        {
          "keyName": "pokemon_pkey",
          "columnNames": [
            "id"
          ],
          "composite": false,
          "constraint": true,
          "primary": true,
          "unique": true
        }
      ],
      "checks": [],
      "foreignKeys": {},
      "nativeEnums": {}
    },
    {
      "columns": {
        "id": {
          "name": "id",
          "type": "serial",
          "unsigned": false,
          "autoincrement": true,
          "primary": true,
          "nullable": false,
          "mappedType": "integer"
        },
        "slug": {
          "name": "slug",
          "type": "varchar(255)",
          "unsigned": false,
          "autoincrement": false,
          "primary": false,
          "nullable": false,
          "length": 255,
          "mappedType": "string"
        },
        "name": {
          "name": "name",
          "type": "varchar(255)",
          "unsigned": false,
          "autoincrement": false,
          "primary": false,
          "nullable": false,
          "length": 255,
          "mappedType": "string"
        }
      },
      "name": "pokemon_type",
      "schema": "public",
      "indexes": [
        {
          "columnNames": [
            "slug"
          ],
          "composite": false,
          "keyName": "pokemon_type_slug_index",
          "constraint": false,
          "primary": false,
          "unique": false
        },
        {
          "columnNames": [
            "slug"
          ],
          "composite": false,
          "keyName": "pokemon_type_slug_unique",
          "constraint": true,
          "primary": false,
          "unique": true
        },
        {
          "columnNames": [
            "name"
          ],
          "composite": false,
          "keyName": "pokemon_type_name_unique",
          "constraint": true,
          "primary": false,
          "unique": true
        },
        {
          "keyName": "pokemon_type_pkey",
          "columnNames": [
            "id"
          ],
          "composite": false,
          "constraint": true,
          "primary": true,
          "unique": true
        }
      ],
      "checks": [],
      "foreignKeys": {},
      "nativeEnums": {}
    }
  ],
  "nativeEnums": {}
}
